time_convert/LunarSolarConverter.py
time_convert/RangeTimeEnum.py
time_convert/StringPreHandler.py
time_convert/Test.py
time_convert/TimeNormalizer.py
time_convert/TimePoint.py
time_convert/TimeUnit.py
time_convert/__init__.py
time_convert/version.py
time_convert/resource/holi_lunar.json
time_convert/resource/holi_solar.json
time_convert/resource/reg.pkl
time_convert/resource/regex.txt
time_convert-1.2.5.dist-info/METADATA
time_convert-1.2.5.dist-info/WHEEL
time_convert-1.2.5.dist-info/top_level.txt
time_convert-1.2.5.dist-info/RECORD
