Metadata-Version: 2.1
Name: time-convert
Version: 1.2.5
Summary: Time convert for Chinese text
Home-page: https://github.com/charlesXu86/Time_Convert
Author: xu
Author-email: charlesxu86@163.com
License: MIT Licence
Keywords: time,nlp
Platform: any
Classifier: Development Status :: 5 - Production/Stable
Classifier: License :: OSI Approved :: MIT License
Classifier: Programming Language :: Python
Classifier: Programming Language :: Python :: 3
Classifier: Programming Language :: Python :: 3.5
Classifier: Programming Language :: Python :: 3.6
Classifier: Programming Language :: Python :: 3.7
Classifier: Programming Language :: Python :: Implementation :: CPython
Classifier: Programming Language :: Python :: Implementation :: PyPy
Requires-Dist: regex (>=2017)
Requires-Dist: arrow (==0.13.1)
